glibs_mail-1.1.0-py3.9-nspkg.pth
glibs/mail/__init__.py
glibs/mail/sendgrid_client.py
glibs_mail-1.1.0.dist-info/METADATA
glibs_mail-1.1.0.dist-info/WHEEL
glibs_mail-1.1.0.dist-info/namespace_packages.txt
glibs_mail-1.1.0.dist-info/top_level.txt
glibs_mail-1.1.0.dist-info/RECORD
